{"ip":0,"fr":60,"v":"5.1.20","assets":[],"layers":[{"ty":4,"nm":"pc","ip":0,"st":0,"ind":7,"hix":7,"ks":{"o":{"a":0,"k":100},"or":{"a":0,"k":[0,0,0]},"a":{"a":0,"k":[26,76,0]},"p":{"s":true,"x":{"a":0,"k":25},"y":{"a":0,"k":437}},"rx":{"a":0,"k":0},"ry":{"a":0,"k":0},"rz":{"a":0,"k":0},"s":{"a":0,"k":[100,100,100]}},"shapes":[{"ty":"gr","nm":"pc shape group","it":[{"ty":"sh","ks":{"a":0,"k":{"c":true,"v":[[0,149.981337],[13.0139828,127.006805],[24.0524962,121.137754],[5.64584777,122.660019],[12.0898175,127.006805],[6.99602425,133.586739],[0.406712414,143.894561]],"i":[[0,0],[0,0],[0,0],[0,0],[0,0],[0,0],[0,0]],"o":[[0,0],[0,0],[0,0],[0,0],[0,0],[0,0],[0,0]]}}},{"ty":"st","o":{"a":0,"k":100},"c":{"a":0,"k":[0.8117647058823529,0.8117647058823529,0.8117647058823529,1]},"lc":3,"lj":1,"ml":1,"w":{"a":0,"k":1}},{"ty":"fl","o":{"a":0,"k":100},"r":2,"c":{"a":0,"k":[0.803921568627451,0.803921568627451,0.803921568627451,1]}},{"ty":"tr","o":{"a":0,"k":100},"a":{"a":0,"k":[0,0]},"s":{"a":0,"k":[100,100]},"p":{"a":0,"k":[1,2]},"r":{"a":0,"k":0}}]},{"ty":"gr","nm":"pc shape group","it":[{"ty":"sh","ks":{"a":0,"k":{"c":true,"v":[[4,122.8163],[0.406712414,144.558967],[0.406712414,149],[13.5853361,122.8163]],"i":[[0,0],[0,0],[0,0],[0,0]],"o":[[0,0],[0,0],[0,0],[0,0]]}}},{"ty":"st","o":{"a":0,"k":100},"c":{"a":0,"k":[0.9019607843137255,0.9019607843137255,0.9019607843137255,1]},"lc":3,"lj":1,"ml":1,"w":{"a":0,"k":1}},{"ty":"fl","o":{"a":0,"k":100},"r":2,"c":{"a":0,"k":[0.9019607843137255,0.9019607843137255,0.9019607843137255,1]}},{"ty":"tr","o":{"a":0,"k":100},"a":{"a":0,"k":[0,0]},"s":{"a":0,"k":[100,100]},"p":{"a":0,"k":[1,2]},"r":{"a":0,"k":0}}]},{"ty":"gr","nm":"pc shape group","it":[{"ty":"sh","ks":{"a":0,"k":{"c":true,"v":[[4.54833115,122.397154],[15.6612955,115.660019],[24.8377462,120.212713],[4.841951,122.660019]],"i":[[0,0],[0,0],[0,0],[0,0]],"o":[[0,0],[0,0],[0,0],[0,0]]}}},{"ty":"st","o":{"a":0,"k":100},"c":{"a":0,"k":[0.9019607843137255,0.9019607843137255,0.9019607843137255,1]},"lc":3,"lj":1,"ml":1,"w":{"a":0,"k":1}},{"ty":"fl","o":{"a":0,"k":100},"r":2,"c":{"a":0,"k":[0.9019607843137255,0.9019607843137255,0.9019607843137255,1]}},{"ty":"tr","o":{"a":0,"k":100},"a":{"a":0,"k":[0,0]},"s":{"a":0,"k":[100,100]},"p":{"a":0,"k":[1,2]},"r":{"a":0,"k":0}}]},{"ty":"gr","nm":"pc shape group","it":[{"ty":"sh","ks":{"a":0,"k":{"c":true,"v":[[44.7845651,135.993131],[41.0427481,64.5950086],[39.9917826,63.648715],[39.1096065,64.2914131],[17.7575988,120.351946],[17.7575988,120.351946]],"i":[[0,0],[0,0],[0.5515278999999964,-0.02890430000000066],[0.14091230000000365,-0.36997079999999727],[0,0],[0,0]],"o":[[0,0],[-0.028904399999994723,-0.5515278999999964],[-0.3953546999999986,0.02071969999999368],[0,0],[0,0],[0,0]]}}},{"ty":"st","o":{"a":0,"k":0},"w":{"a":0,"k":0},"c":{"a":0,"k":[0,0,0,0]},"lc":3,"lj":1,"ml":1},{"ty":"fl","o":{"a":0,"k":100},"r":2,"c":{"a":0,"k":[0.9607843137254902,0.9607843137254902,0.9607843137254902,1]}},{"ty":"tr","o":{"a":0,"k":100},"a":{"a":0,"k":[0,0]},"s":{"a":0,"k":[100,100]},"p":{"a":0,"k":[6.168,0.498]},"r":{"a":0,"k":2.9793805346802804}}]},{"ty":"gr","nm":"pc shape group","it":[{"ty":"sh","ks":{"a":0,"k":{"c":true,"v":[[4,36.1659726],[49,0],[49,76.4588848],[49,145],[4,115.571694]],"i":[[0,0],[0,0],[0,-17.27882180000001],[0,-28.415255000000002],[0,0]],"o":[[0,0],[0,33.6937681],[0,17.27882179999999],[0,0],[0,0]]}}},{"ty":"st","o":{"a":0,"k":100},"c":{"a":0,"k":[0.26666666666666666,0.26666666666666666,0.26666666666666666,1]},"lc":3,"lj":2,"ml":1,"w":{"a":0,"k":3}},{"ty":"fl","o":{"a":0,"k":100},"r":2,"c":{"a":0,"k":[1,1,1,1]}},{"ty":"tr","o":{"a":0,"k":100},"a":{"a":0,"k":[0,0]},"s":{"a":0,"k":[100,100]},"p":{"a":0,"k":[1,2]},"r":{"a":0,"k":0}}]}],"op":179},{"ty":4,"nm":"Path","ip":0,"st":0,"ind":6,"hix":3,"ks":{"o":{"a":0,"k":100},"or":{"a":0,"k":[0,0,0]},"a":{"a":0,"k":[4.5,6.5,0]},"p":{"s":true,"x":{"a":0,"k":260.268},"y":{"a":0,"k":215.91}},"rx":{"a":0,"k":0},"ry":{"a":0,"k":0},"rz":{"a":0,"k":0},"s":{"a":0,"k":[100,100]}},"shapes":[{"ty":"gr","nm":"Path shape group","it":[{"ty":"sh","ks":{"a":0,"k":{"c":true,"v":[[17.6846984,90.4413732],[25.0324451,92.0421958],[32.0921363,91.5267732],[25.4111578,87.6443441]],"i":[[2.8869840000000018,-2.006067299999998],[-3.808650700000001,-0.2934677000000079],[-1.8593617999999985,0.5414239000000123],[2.2639888,0.14138130000000615]],"o":[[1.5721317,0.6309315000000026],[2.216219299999999,0.17076609999999448],[-2.1899967999999994,-2.4469047999999987],[-2.263988900000001,-0.14138129999999194]]}}},{"ty":"st","o":{"a":0,"k":0},"w":{"a":0,"k":0},"c":{"a":0,"k":[0,0,0,0]},"lc":3,"lj":1,"ml":1},{"ty":"fl","o":{"a":0,"k":100},"r":2,"c":{"a":0,"k":[0,0,0,1]}},{"ty":"tr","o":{"a":0,"k":100},"a":{"a":0,"k":[0,0]},"s":{"a":0,"k":[100,100]},"p":{"a":0,"k":[60.384,-69.072]},"r":{"a":0,"k":52.024567797878746}}]}],"op":179},{"ty":4,"nm":"Oval","ip":0,"st":0,"ind":5,"hix":4,"ks":{"o":{"a":0,"k":100},"or":{"a":0,"k":[0,0,0]},"a":{"a":0,"k":[7,7,0]},"p":{"s":true,"x":{"a":0,"k":289.268},"y":{"a":0,"k":209.41}},"rx":{"a":0,"k":0},"ry":{"a":0,"k":0},"rz":{"a":0,"k":0},"s":{"a":0,"k":[100,100]}},"shapes":[{"ty":"gr","nm":"Oval shape group","it":[{"ty":"el","p":{"a":0,"k":[54,84]},"s":{"a":0,"k":[11.26006482,12.6614116]}},{"ty":"st","o":{"a":0,"k":100},"c":{"a":0,"k":[0,0,0,1]},"lc":3,"lj":1,"ml":1,"w":{"a":0,"k":1}},{"ty":"fl","o":{"a":0,"k":100},"r":2,"c":{"a":0,"k":[0,0,0,1]}},{"ty":"tr","o":{"a":0,"k":100},"a":{"a":0,"k":[0,0]},"s":{"a":0,"k":[100,100]},"p":{"a":0,"k":[-71.418,-54.827]},"r":{"a":0,"k":341.02447966186594}}]}],"op":179},{"ty":4,"nm":"Path 3","ip":0,"st":0,"ind":4,"hix":5,"ks":{"o":{"a":0,"k":100},"or":{"a":0,"k":[0,0,0]},"a":{"a":0,"k":[12.5,5,0]},"p":{"s":true,"x":{"a":0,"k":275.268},"y":{"a":0,"k":216.41}},"rx":{"a":0,"k":0},"ry":{"a":0,"k":0},"rz":{"a":0,"k":0},"s":{"a":0,"k":[100,100,100]}},"shapes":[{"ty":"gr","nm":"Path 3 shape group","it":[{"ty":"sh","ks":{"a":0,"k":{"c":false,"v":[[27.1244275,94.3202734],[40.5256667,92.5074604],[50.9531509,87.2686616]],"i":[[0,0],[-2.660636799999999,0.8177126000000072],[-4.291019299999995,2.6748197999999945]],"o":[[6.273522600000003,-0.3908294000000012],[2.6606369,-0.8177127000000013],[0,0]]}}},{"ty":"st","o":{"a":0,"k":100},"c":{"a":0,"k":[0,0,0,1]},"lc":3,"lj":1,"ml":1,"w":{"a":0,"k":2}},{"ty":"fl","o":{"a":0,"k":0},"c":{"a":0,"k":[0,0,0,0]},"r":1},{"ty":"tr","o":{"a":0,"k":100},"a":{"a":0,"k":[0,0]},"s":{"a":0,"k":[100,100]},"p":{"a":0,"k":[-27,-86]},"r":{"a":0,"k":0}}]}],"op":179},{"ty":4,"nm":"head","ip":0,"st":0,"ind":3,"hix":2,"ks":{"o":{"a":0,"k":100},"or":{"a":0,"k":[0,0,0]},"a":{"a":0,"k":[47,43.5,0]},"p":{"s":true,"x":{"a":0,"k":299.768},"y":{"a":0,"k":187.5}},"rx":{"a":0,"k":0},"ry":{"a":0,"k":0},"rz":{"a":0,"k":0},"s":{"a":0,"k":[100,100,100]}},"shapes":[{"ty":"gr","nm":"head shape group","it":[{"ty":"el","p":{"a":0,"k":[63,61]},"s":{"a":0,"k":[71.6986176,101.6324584]}},{"ty":"st","o":{"a":0,"k":100},"c":{"a":0,"k":[0.20784313725490197,0.20784313725490197,0.20784313725490197,1]},"lc":3,"lj":1,"ml":1,"w":{"a":0,"k":2}},{"ty":"fl","o":{"a":0,"k":100},"r":2,"c":{"a":0,"k":[1,1,1,1]}},{"ty":"tr","o":{"a":0,"k":100},"a":{"a":0,"k":[0,0]},"s":{"a":0,"k":[100,100]},"p":{"a":0,"k":[56.032,-44.738]},"r":{"a":0,"k":52.024567797878746}}]}],"op":179},{"ty":4,"nm":"base","ip":0,"st":0,"ind":2,"hix":6,"ks":{"o":{"a":0,"k":100},"or":{"a":0,"k":[0,0,0]},"a":{"a":0,"k":[155,169,0]},"p":{"s":true,"x":{"a":0,"k":348.012},"y":{"a":0,"k":346}},"rx":{"a":0,"k":0},"ry":{"a":0,"k":0},"rz":{"a":0,"k":0},"s":{"a":0,"k":[100,100,100]}},"shapes":[{"ty":"gr","nm":"base shape group","it":[{"ty":"sh","ks":{"a":0,"k":{"c":true,"v":[[106.789127,79.9441184],[134.04574,160.723798],[136.653651,199.505291],[60.873362,157.186995]],"i":[[-44.27540379999999,22.42638260000001],[-4.475150999999983,-25.869548999999978],[0.4263960000000111,-13.339071999999987],[13.699804400000005,18.87130400000001]],"o":[[13.695925000000003,27.983570600000007],[2.1650040000000104,12.51525700000002],[-36.82038829999999,-9.340892999999994],[-13.6648937,-29.068869000000007]]}}},{"ty":"st","o":{"a":0,"k":0},"w":{"a":0,"k":0},"c":{"a":0,"k":[0,0,0,0]},"lc":3,"lj":1,"ml":1},{"ty":"fl","o":{"a":0,"k":100},"r":2,"c":{"a":0,"k":[0.984313725490196,0.984313725490196,0.984313725490196,1]}},{"ty":"tr","o":{"a":0,"k":100},"a":{"a":0,"k":[0,0]},"s":{"a":0,"k":[100,100]},"p":{"a":0,"k":[169.968,35.902]},"r":{"a":0,"k":0}}]},{"ty":"gr","nm":"base shape group","it":[{"ty":"sh","ks":{"a":0,"k":{"c":true,"v":[[27.9985038,300.847334],[1.43150016,251.609586],[4.87973024,187.867651],[19.114024,117.655968],[19.114024,49.9224526],[27.9985038,1.95168014],[77.0277379,26.1736522],[135.408572,160.723798],[113.339899,300.847334]],"i":[[0,0],[2.7163190200000003,13.274443999999988],[-5.015139069,29.22018],[-1.7689486000000016,17.14296300000001],[1.768948599999998,28.012714400000007],[-13.308641500000002,6.06592611],[-19.377514600000005,-22.21390749],[-7.2753060000000005,-42.056432999999984],[21.987754999999993,-51.359256999999985]],"o":[[-14.995016800000002,-19.55072100000001],[-2.71631902,-13.27444300000002],[7.720580560000001,-29.664826000000005],[1.768948599999998,-17.142961999999997],[-7.385655,-25.9145889],[13.3086415,-6.065926119999999],[31.6452501,47.643664199999996],[7.2753060000000005,42.056433],[0,0]]}}},{"ty":"st","o":{"a":0,"k":100},"c":{"a":0,"k":[0.20784313725490197,0.20784313725490197,0.20784313725490197,1]},"lc":3,"lj":1,"ml":1,"w":{"a":0,"k":2}},{"ty":"fl","o":{"a":0,"k":100},"r":2,"c":{"a":0,"k":[1,1,1,1]}},{"ty":"tr","o":{"a":0,"k":100},"a":{"a":0,"k":[0,0]},"s":{"a":0,"k":[100,100]},"p":{"a":0,"k":[169.968,35.902]},"r":{"a":0,"k":0}}]},{"ty":"gr","nm":"base shape group","it":[{"ty":"sh","ks":{"a":0,"k":{"c":true,"v":[[36.741449,335.749565],[0.594597462,247.815522],[62.4911873,109.096508],[78.3552059,58.3210821],[93.4654762,32.137092],[129.005007,4.73227625],[174.6489,4.73227625],[298.612254,175.05281],[279.309497,335.749565]],"i":[[0,0],[4.158723938,35.97699],[-9.8993228,25.067890000000006],[-3.882553299999998,7.597501199999996],[-3.1842001999999923,3.974770399999997],[-9.460614000000007,0],[-31.45297099999999,-9.971858600000001],[-23.478203000000008,-89.5278068],[28.520639999999958,-47.445966]],"o":[[-19.939177100000002,-22.64570500000002],[-6.238085912000001,-53.965485],[9.8993228,-25.067889699999995],[6.889313299999998,-13.481223],[14.232406800000007,-18.269877200000003],[14.190922,0],[31.45297099999999,9.97185865],[15.652134999999987,59.685204],[0,0]]}}},{"ty":"st","o":{"a":0,"k":100},"c":{"a":0,"k":[0.20784313725490197,0.20784313725490197,0.20784313725490197,1]},"lc":3,"lj":1,"ml":1,"w":{"a":0,"k":2}},{"ty":"fl","o":{"a":0,"k":100},"r":2,"c":{"a":0,"k":[1,1,1,1]}},{"ty":"tr","o":{"a":0,"k":100},"a":{"a":0,"k":[0,0]},"s":{"a":0,"k":[100,100]},"p":{"a":0,"k":[1,1]},"r":{"a":0,"k":0}}]}],"op":179},{"ty":4,"nm":"left hand","ip":0,"st":0,"ind":1,"hix":1,"ks":{"o":{"a":0,"k":100},"or":{"a":0,"k":[0,0,0]},"a":{"a":0,"k":[136,120,0]},"p":{"s":true,"x":{"a":1,"k":[{"t":0,"s":[298.768],"e":[192.553],"i":{"x":[0.515],"y":[0.955]},"o":{"x":[0.455],"y":[0.03]}},{"t":59,"s":[192.553],"e":[177.553],"i":{"x":[0.515],"y":[0.955]},"o":{"x":[0.455],"y":[0.03]}},{"t":90,"s":[177.553],"e":[192.253],"i":{"x":[0.515],"y":[0.955]},"o":{"x":[0.455],"y":[0.03]}},{"t":120,"s":[192.253],"e":[295.768],"i":{"x":[0.515],"y":[0.955]},"o":{"x":[0.455],"y":[0.03]}},{"t":179}]},"y":{"a":1,"k":[{"t":0,"s":[360.781],"e":[350.907],"i":{"x":[0.515],"y":[0.955]},"o":{"x":[0.455],"y":[0.03]}},{"t":59,"s":[350.907],"e":[347.907],"i":{"x":[0.515],"y":[0.955]},"o":{"x":[0.455],"y":[0.03]}},{"t":90,"s":[347.907],"e":[350.907],"i":{"x":[0.515],"y":[0.955]},"o":{"x":[0.455],"y":[0.03]}},{"t":120,"s":[350.907],"e":[394.781],"i":{"x":[0.515],"y":[0.955]},"o":{"x":[0.455],"y":[0.03]}},{"t":179}]}},"rx":{"a":0,"k":0},"ry":{"a":0,"k":0},"rz":{"a":1,"k":[{"t":0,"s":[-48.70141258611997],"e":[-5.7868737308213145],"i":{"x":[0.515],"y":[0.955]},"o":{"x":[0.455],"y":[0.03]}},{"t":59,"s":[-5.7868737308213145],"e":[0.6875493541569879],"i":{"x":[0.515],"y":[0.955]},"o":{"x":[0.455],"y":[0.03]}},{"t":90,"s":[0.6875493541569879],"e":[-5.7868737308213145],"i":{"x":[0.515],"y":[0.955]},"o":{"x":[0.455],"y":[0.03]}},{"t":120,"s":[-5.7868737308213145],"e":[-48.70141258611997],"i":{"x":[0.515],"y":[0.955]},"o":{"x":[0.455],"y":[0.03]}},{"t":179}]},"s":{"a":1,"k":[{"t":0,"s":[100,100],"e":[100,100],"i":{"x":[0.515,0.515],"y":[0.955,0.955]},"o":{"x":[0.455,0.455],"y":[0.03,0.03]}},{"t":59,"s":[100,100],"e":[100,100],"i":{"x":[1,1],"y":[1,1]},"o":{"x":[0,0],"y":[0,0]}},{"t":131,"s":[100,100],"e":[0,0],"i":{"x":[0.515,0.515],"y":[0.955,0.955]},"o":{"x":[0.455,0.455],"y":[0.03,0.03]}},{"t":179}]}},"shapes":[{"ty":"gr","nm":"left hand shape group","it":[{"ty":"sh","ks":{"a":0,"k":{"c":false,"v":[[63.2969961,188.849353],[39.3741199,198.246835],[15.8898694,200.001284],[5.61753547,187.730576],[10.110412,180.830891],[39.3958282,169.707684],[56.9954984,159.200437],[70.4937643,150.854099]],"i":[[0,0],[6.949790300000004,-1.9332650000000058],[9.1473739,1.729551000000015],[1.1304092099999998,3.377225999999979],[-3.74885714,2.3483059999999796],[-6.9776132999999945,3.2278200000000083],[-5.329979800000004,4.232533000000018],[-4.579151799999991,-0.47164399999999773]],"o":[[-8.998793800000001,4.3317229999999824],[-10.424685499999995,2.899895999999984],[-9.14737397,-1.729549999999989],[-0.7536061299999997,-2.251484000000005],[12.545997499999999,-4.187652000000014],[5.244887200000001,-2.4262669999999957],[5.306246399999999,-4.213686999999993],[0,0]]}}},{"ty":"st","o":{"a":0,"k":100},"c":{"a":0,"k":[0.1607843137254902,0.1607843137254902,0.1607843137254902,1]},"lc":2,"lj":1,"ml":1,"w":{"a":0,"k":2}},{"ty":"fl","o":{"a":0,"k":100},"r":2,"c":{"a":0,"k":[1,1,1,1]}},{"ty":"tr","o":{"a":0,"k":100},"a":{"a":0,"k":[0,0]},"s":{"a":0,"k":[100,100]},"p":{"a":0,"k":[-45.595,14.048]},"r":{"a":0,"k":346.98324073122654}}]},{"ty":"gr","nm":"left hand shape group","it":[{"ty":"sh","ks":{"a":0,"k":{"c":false,"v":[[109.857383,191.064239],[99.5974363,206.480642],[97.9212257,220.819544],[128.199482,204.933625]],"i":[[0,0],[2.899650699999995,-1.7184509999999875],[-3.9451844999999963,-3.1913120000000106],[-0.37803799999998944,1.2271669999999801]],"o":[[-3.9403130000000033,8.559151000000014],[-7.394121900000002,4.382056000000006],[9.498095300000003,7.683134999999993],[0,0]]}}},{"ty":"st","o":{"a":0,"k":100},"c":{"a":0,"k":[0.1607843137254902,0.1607843137254902,0.1607843137254902,1]},"lc":2,"lj":1,"ml":1,"w":{"a":0,"k":2}},{"ty":"fl","o":{"a":0,"k":100},"r":2,"c":{"a":0,"k":[1,1,1,1]}},{"ty":"tr","o":{"a":0,"k":100},"a":{"a":0,"k":[0,0]},"s":{"a":0,"k":[100,100]},"p":{"a":0,"k":[-125.598,160.153]},"r":{"a":0,"k":310.02746294528845}}]},{"ty":"gr","nm":"left hand shape group","it":[{"ty":"sh","ks":{"a":0,"k":{"c":true,"v":[[53.3482365,190.693362],[58.6403352,211.993538],[71.2373101,232.055785],[98.0586952,236.576395],[118.782215,224.868109],[120.328904,217.294471],[117.283568,217.647259],[114.507371,217.294471],[114.742162,212.418519],[118.132216,210.604347],[131.096714,212.418519],[230.346106,115.128892],[277.829059,28.810856],[265.202622,1.49836695],[234.277839,11.4369815],[150.792251,93.1987332],[79.9577048,130.838836],[63.7727663,140.26228],[53.3482365,160.041065]],"i":[[0,0],[-0.8505439000000052,-2.8869200000000035],[-7.464543800000001,-5.616822999999982],[-8.265083500000003,2.423605000000009],[-3.2388489999999877,2.8042509999999936],[0.7344870000000014,1.3012720000000115],[2.173085999999998,0.0034290000000112286],[0.35758999999998764,0.4492050000000063],[-1.3921549999999883,2.453671999999983],[-1.3319330000000065,-0.42633200000000215],[-31.15562899999999,3.895738999999992],[-25.495713999999992,32.383852000000005],[-6.049552999999946,25.021741499999997],[8.417624999999987,3.7586854599999997],[12.198896999999988,-10.38442848],[34.115519000000006,-16.59725010000001],[13.1075108,-8.49615199999998],[3.569352699999996,-3.201904000000013],[3.3803338000000025,-9.983952000000016]],"o":[[2.677521900000002,11.313197000000002],[1.2758158999999978,4.3303809999999885],[7.464543899999995,5.616822000000013],[8.2650838,-2.4236049999999807],[3.2388499999999993,-2.8042509999999936],[-0.35644699999998863,-0.6315089999999941],[-0.8121189999999956,-0.001280999999977439],[-0.35759000000000185,-0.44920499999997787],[0.9281030000000072,-1.6357800000000111],[-22.512630400000006,5.105187000000001],[46.73344300000002,-5.843606999999992],[25.605749000000003,-32.52361579999999],[0,-14.4496406],[-8.417625000000044,-3.7586854599999997],[-21.541539,37.9105843],[-34.11551999999999,16.5972498],[-7.2206063,3.0803920000000176],[-3.569352700000003,3.2019039999999848],[0,0]]}}},{"ty":"st","o":{"a":0,"k":100},"c":{"a":0,"k":[0.1607843137254902,0.1607843137254902,0.1607843137254902,1]},"lc":3,"lj":1,"ml":1,"w":{"a":0,"k":2}},{"ty":"fl","o":{"a":0,"k":100},"r":2,"c":{"a":0,"k":[1,1,1,1]}},{"ty":"tr","o":{"a":0,"k":100},"a":{"a":0,"k":[0,0]},"s":{"a":0,"k":[100,100]},"p":{"a":0,"k":[-7,1]},"r":{"a":0,"k":0}}]}],"op":179}],"op":179,"w":512,"h":512}